jrl/__init__.py
jrl/config.py
jrl/conversions.py
jrl/evaluation.py
jrl/geometry.py
jrl/robot.py
jrl/robots.py
jrl/urdf_utils.py
jrl/utils.py
jrl/urdfs/README.md
jrl/urdfs/baxter/baxter.urdf
jrl/urdfs/baxter/info.md
jrl/urdfs/baxter/meshes/base/PEDESTAL.DAE
jrl/urdfs/baxter/meshes/base/PEDESTAL.STL
jrl/urdfs/baxter/meshes/base/pedestal_link_collision.DAE
jrl/urdfs/baxter/meshes/base/pedestal_link_collision.STL
jrl/urdfs/baxter/meshes/head/H0.DAE
jrl/urdfs/baxter/meshes/head/H0.STL
jrl/urdfs/baxter/meshes/head/H1.DAE
jrl/urdfs/baxter/meshes/head/H1.STL
jrl/urdfs/baxter/meshes/lower_elbow/E1.DAE
jrl/urdfs/baxter/meshes/lower_elbow/E1.STL
jrl/urdfs/baxter/meshes/lower_forearm/W1.DAE
jrl/urdfs/baxter/meshes/lower_forearm/W1.STL
jrl/urdfs/baxter/meshes/lower_shoulder/S1.DAE
jrl/urdfs/baxter/meshes/lower_shoulder/S1.STL
jrl/urdfs/baxter/meshes/torso/base_link.DAE
jrl/urdfs/baxter/meshes/torso/base_link.STL
jrl/urdfs/baxter/meshes/torso/base_link_collision.DAE
jrl/urdfs/baxter/meshes/torso/base_link_collision.STL
jrl/urdfs/baxter/meshes/upper_elbow/E0.DAE
jrl/urdfs/baxter/meshes/upper_elbow/E0.STL
jrl/urdfs/baxter/meshes/upper_forearm/W0.DAE
jrl/urdfs/baxter/meshes/upper_forearm/W0.STL
jrl/urdfs/baxter/meshes/upper_shoulder/S0.DAE
jrl/urdfs/baxter/meshes/upper_shoulder/S0.STL
jrl/urdfs/baxter/meshes/wrist/W2.DAE
jrl/urdfs/baxter/meshes/wrist/W2.STL
jrl/urdfs/fetch/README.md
jrl/urdfs/fetch/fetch.pdf
jrl/urdfs/fetch/fetch.urdf
jrl/urdfs/fetch/fetch_formatted.urdf
jrl/urdfs/fetch/capsules/base_link_collision.png
jrl/urdfs/fetch/capsules/base_link_collision.txt
jrl/urdfs/fetch/capsules/bellows_link_collision.png
jrl/urdfs/fetch/capsules/bellows_link_collision.txt
jrl/urdfs/fetch/capsules/elbow_flex_link_collision.png
jrl/urdfs/fetch/capsules/elbow_flex_link_collision.txt
jrl/urdfs/fetch/capsules/forearm_roll_link_collision.png
jrl/urdfs/fetch/capsules/forearm_roll_link_collision.txt
jrl/urdfs/fetch/capsules/gripper_link_collision.png
jrl-0.0.9.dist-info/LICENSE.txt
jrl-0.0.9.dist-info/METADATA
jrl-0.0.9.dist-info/WHEEL
jrl-0.0.9.dist-info/top_level.txt
jrl-0.0.9.dist-info/RECORD
