Metadata-Version: 2.1
Name: jrl
Version: 0.0.9
Summary: Jeremy's Robotics Library
Home-page: https://github.com/jstmn/jrl
Author: Jeremy Morgan
Author-email: jsmorgan6@gmail.com
License: LICENSE.txt
License-File: LICENSE.txt
Requires-Dist: klampt
Requires-Dist: numpy
Requires-Dist: torch (==2.0.1)
Requires-Dist: more-itertools
Requires-Dist: roma
Requires-Dist: tqdm
Provides-Extra: dev
Requires-Dist: black (==22.12.0) ; extra == 'dev'
Requires-Dist: pylint (==2.15.9) ; extra == 'dev'
Requires-Dist: PyQt5 (==5.15.7) ; extra == 'dev'
Requires-Dist: kinpy (==0.2.0) ; extra == 'dev'
Requires-Dist: pandas (==1.5.3) ; extra == 'dev'
Requires-Dist: matplotlib (==3.6.2) ; extra == 'dev'
Requires-Dist: tabulate (==0.9.0) ; extra == 'dev'
Requires-Dist: jupyter (==1.0.0) ; extra == 'dev'
Requires-Dist: torchviz (==0.0.2) ; extra == 'dev'
Requires-Dist: meshcat (==0.3.2) ; extra == 'dev'
